metart/__init__.py
metart/app/__init__.py
metart/app/classification.py
metart/app/detection.py
metart/app/face_detection.py
metart/app/face_embedding.py
metart/app/face_recognition.py
metart/app/obb_detection.py
metart/app/person_detection.py
metart/app/quantization.py
metart/app/segment.py
metart/model_zoo/__init__.py
metart/model_zoo/model.py
metart/utils/__init__.py
metart/utils/general.py
meta_rt-0.1.4.dist-info/METADATA
meta_rt-0.1.4.dist-info/WHEEL
meta_rt-0.1.4.dist-info/top_level.txt
meta_rt-0.1.4.dist-info/zip-safe
meta_rt-0.1.4.dist-info/RECORD
