Metadata-Version: 2.1
Name: meta-rt
Version: 0.1.4
Summary: Meta TR Toolkit
Home-page: https://github.com/CachCheng/metart
Author: CachCheng
Author-email: tkggpdc2007@163.com
License: Apache-2.0
Platform: UNKNOWN
Requires-Dist: opencv-python
Requires-Dist: setuptools
Requires-Dist: numpy
Requires-Dist: meta-cv
